casaviewer/LICENSE.txt
casaviewer/__init__.py
casaviewer/__main__.py
casaviewer/imview.py
casaviewer/msview.py
casaviewer/__bin__/casaviewer-x86_64.AppImage
casaviewer/gotasks/__init__.py
casaviewer/gotasks/imview.py
casaviewer/gotasks/msview.py
casaviewer/private/config.py
casaviewer/private/img_pb2.py
casaviewer/private/img_pb2_grpc.py
casaviewer/private/ping_pb2.py
casaviewer/private/ping_pb2_grpc.py
casaviewer/private/shutdown_pb2.py
casaviewer/private/shutdown_pb2_grpc.py
casaviewer/private/task_imview.py
casaviewer/private/task_msview.py
casaviewer/private/viewertool.py
casaviewer-2.4.4.dist-info/METADATA
casaviewer-2.4.4.dist-info/WHEEL
casaviewer-2.4.4.dist-info/top_level.txt
casaviewer-2.4.4.dist-info/RECORD
